{
  "graduateAlumni": [],
  "undergradAlumni": [
    {
      "name": "강병오",
      "degrees": ["ur"],
      "cohort": "1기",
      "periods": {"ur": "2025.12.22 – 2026.03.01"},
      "education": [{"degree": "bs", "school": "Kyung Hee University", "year": "2026"}],
      "cohortName": "1st Cohort (2025 Winter)",
      "currentPosition": "재학생",
      "project": {"title": "Lorem ipsum dolor sit amet, consectetur adipiscing elit."}
    },
    {
      "name": "고현우",
      "degrees": ["ur"],
      "cohort": "1기",
      "periods": {"ur": "2025.12.22 – 2026.03.01"},
      "education": [{"degree": "bs", "school": "Kyung Hee University", "year": "2026"}],
      "cohortName": "1st Cohort (2025 Winter)",
      "currentPosition": "재학생",
      "project": {"title": "Lorem ipsum dolor sit amet, consectetur adipiscing elit."}
    },
    {
      "name": "김강현",
      "degrees": ["ur"],
      "cohort": "1기",
      "periods": {"ur": "2025.12.22 – 2026.03.01"},
      "education": [{"degree": "bs", "school": "Soongsil University", "year": "2026"}],
      "cohortName": "1st Cohort (2025 Winter)",
      "currentPosition": "재학생",
      "project": {"title": "Lorem ipsum dolor sit amet, consectetur adipiscing elit."}
    },
    {
      "name": "김다인",
      "degrees": ["ur"],
      "cohort": "1기",
      "periods": {"ur": "2025.12.22 – 2026.03.01"},
      "education": [{"degree": "bs", "school": "Hongik University", "year": "2026"}],
      "cohortName": "1st Cohort (2025 Winter)",
      "currentPosition": "재학생",
      "project": {"title": "Lorem ipsum dolor sit amet, consectetur adipiscing elit."}
    },
    {
      "name": "김연후",
      "degrees": ["ur"],
      "cohort": "1기",
      "periods": {"ur": "2025.12.22 – 2026.03.01"},
      "education": [{"degree": "bs", "school": "Hanyang University ERICA Campus", "year": "2026"}],
      "cohortName": "1st Cohort (2025 Winter)",
      "currentPosition": "재학생",
      "project": {"title": "Lorem ipsum dolor sit amet, consectetur adipiscing elit."}
    },
    {
      "name": "김재엽",
      "degrees": ["ur"],
      "cohort": "1기",
      "periods": {"ur": "2025.12.22 – 2026.03.01"},
      "education": [{"degree": "bs", "school": "Hanyang University", "year": "2026"}],
      "cohortName": "1st Cohort (2025 Winter)",
      "currentPosition": "재학생",
      "project": {"title": "Lorem ipsum dolor sit amet, consectetur adipiscing elit."}
    },
    {
      "name": "박성수",
      "degrees": ["ur"],
      "cohort": "1기",
      "periods": {"ur": "2025.12.22 – 2026.03.01"},
      "education": [{"degree": "bs", "school": "Kyung Hee University", "year": "2026"}],
      "cohortName": "1st Cohort (2025 Winter)",
      "currentPosition": "Graduate School\nKorea University",
      "project": {"title": "Lorem ipsum dolor sit amet, consectetur adipiscing elit."}
    },
    {
      "name": "신경수",
      "degrees": ["ur"],
      "cohort": "1기",
      "periods": {"ur": "2025.12.22 – 2026.03.01"},
      "education": [{"degree": "bs", "school": "Kyung Hee University", "year": "2026"}],
      "cohortName": "1st Cohort (2025 Winter)",
      "currentPosition": "재학생",
      "project": {"title": "Lorem ipsum dolor sit amet, consectetur adipiscing elit."}
    },
    {
      "name": "신정윤",
      "degrees": ["ur"],
      "cohort": "1기",
      "periods": {"ur": "2025.12.22 – 2026.03.01"},
      "education": [{"degree": "bs", "school": "Kyung Hee University", "year": "2026"}],
      "cohortName": "1st Cohort (2025 Winter)",
      "currentPosition": "재학생",
      "project": {"title": "Lorem ipsum dolor sit amet, consectetur adipiscing elit."}
    },
    {
      "name": "심은",
      "degrees": ["ur"],
      "cohort": "1기",
      "periods": {"ur": "2025.12.22 – 2026.03.01"},
      "education": [{"degree": "bs", "school": "Sogang University", "year": "2026"}],
      "cohortName": "1st Cohort (2025 Winter)",
      "currentPosition": "재학생",
      "project": {"title": "Lorem ipsum dolor sit amet, consectetur adipiscing elit."}
    },
    {
      "name": "양동훈",
      "degrees": ["ur"],
      "cohort": "1기",
      "periods": {"ur": "2025.12.22 – 2026.03.01"},
      "education": [{"degree": "bs", "school": "Inha University", "year": "2026"}],
      "cohortName": "1st Cohort (2025 Winter)",
      "currentPosition": "재학생",
      "project": {"title": "Lorem ipsum dolor sit amet, consectetur adipiscing elit."}
    },
    {
      "name": "이성준",
      "degrees": ["ur"],
      "cohort": "1기",
      "periods": {"ur": "2025.12.22 – 2026.03.01"},
      "education": [{"degree": "bs", "school": "Kyung Hee University", "year": "2026"}],
      "cohortName": "1st Cohort (2025 Winter)",
      "currentPosition": "재학생",
      "project": {"title": "Lorem ipsum dolor sit amet, consectetur adipiscing elit."}
    },
    {
      "name": "이수인",
      "degrees": ["ur"],
      "cohort": "1기",
      "periods": {"ur": "2025.12.22 – 2026.03.01"},
      "education": [{"degree": "bs", "school": "Kyung Hee University", "year": "2026"}],
      "cohortName": "1st Cohort (2025 Winter)",
      "currentPosition": "Graduate School\nSeoul National University",
      "project": {"title": "Lorem ipsum dolor sit amet, consectetur adipiscing elit."}
    },
    {
      "name": "이유섭",
      "degrees": ["ur"],
      "cohort": "1기",
      "periods": {"ur": "2025.12.22 – 2026.03.01"},
      "education": [{"degree": "bs", "school": "Korea Advanced Institute of Science and Technology (KAIST)", "year": "2026"}],
      "cohortName": "1st Cohort (2025 Winter)",
      "currentPosition": "재학생",
      "project": {"title": "Lorem ipsum dolor sit amet, consectetur adipiscing elit."}
    },
    {
      "name": "이채은",
      "degrees": ["ur"],
      "cohort": "1기",
      "periods": {"ur": "2025.12.22 – 2026.03.01"},
      "education": [{"degree": "bs", "school": "Gachon University", "year": "2026"}],
      "cohortName": "1st Cohort (2025 Winter)",
      "currentPosition": "재학생",
      "project": {"title": "Lorem ipsum dolor sit amet, consectetur adipiscing elit."}
    },
    {
      "name": "이태경",
      "degrees": ["ur"],
      "cohort": "1기",
      "periods": {"ur": "2025.12.22 – 2026.03.01"},
      "education": [{"degree": "bs", "school": "Kyung Hee University", "year": "2026"}],
      "cohortName": "1st Cohort (2025 Winter)",
      "currentPosition": "Graduate School\nKorea University",
      "project": {"title": "Lorem ipsum dolor sit amet, consectetur adipiscing elit."}
    },
    {
      "name": "임소영",
      "degrees": ["ur"],
      "cohort": "1기",
      "periods": {"ur": "2025.12.22 – 2026.03.01"},
      "education": [{"degree": "bs", "school": "Kyung Hee University", "year": "2026"}],
      "cohortName": "1st Cohort (2025 Winter)",
      "currentPosition": "재학생",
      "project": {"title": "Lorem ipsum dolor sit amet, consectetur adipiscing elit."}
    },
    {
      "name": "정유진",
      "degrees": ["ur"],
      "cohort": "1기",
      "periods": {"ur": "2025.12.22 – 2026.03.01"},
      "education": [{"degree": "bs", "school": "Kyung Hee University", "year": "2026"}],
      "cohortName": "1st Cohort (2025 Winter)",
      "currentPosition": "재학생",
      "project": {"title": "Lorem ipsum dolor sit amet, consectetur adipiscing elit."}
    },
    {
      "name": "조윤수",
      "degrees": ["ur"],
      "cohort": "1기",
      "periods": {"ur": "2025.12.22 – 2026.03.01"},
      "education": [{"degree": "bs", "school": "Kyung Hee University", "year": "2026"}],
      "cohortName": "1st Cohort (2025 Winter)",
      "currentPosition": "재학생",
      "project": {"title": "Lorem ipsum dolor sit amet, consectetur adipiscing elit."}
    },
    {
      "name": "최문혁",
      "degrees": ["ur"],
      "cohort": "1기",
      "periods": {"ur": "2025.12.22 – 2026.03.01"},
      "education": [{"degree": "bs", "school": "Kyung Hee University", "year": "2026"}],
      "cohortName": "1st Cohort (2025 Winter)",
      "currentPosition": "재학생",
      "project": {"title": "Lorem ipsum dolor sit amet, consectetur adipiscing elit."}
    },
    {
      "name": "최진우",
      "degrees": ["ur"],
      "cohort": "1기",
      "periods": {"ur": "2025.12.22 – 2026.03.01"},
      "education": [{"degree": "bs", "school": "Kyung Hee University", "year": "2026"}],
      "cohortName": "1st Cohort (2025 Winter)",
      "currentPosition": "재학생",
      "project": {"title": "Lorem ipsum dolor sit amet, consectetur adipiscing elit."}
    },
    {
      "name": "하승민",
      "degrees": ["ur"],
      "cohort": "1기",
      "periods": {"ur": "2025.12.22 – 2026.03.01"},
      "education": [{"degree": "bs", "school": "Jeonbuk National University", "year": "2026"}],
      "cohortName": "1st Cohort (2025 Winter)",
      "currentPosition": "재학생",
      "project": {"title": "Lorem ipsum dolor sit amet, consectetur adipiscing elit."}
    }
  ],
  "sinceDate": "2025.06.14"
}
